histy/__init__.py
histy/histy.py
histy-1.0.3.dist-info/LICENSE
histy-1.0.3.dist-info/METADATA
histy-1.0.3.dist-info/WHEEL
histy-1.0.3.dist-info/entry_points.txt
histy-1.0.3.dist-info/top_level.txt
histy-1.0.3.dist-info/RECORD
