Metadata-Version: 2.1
Name: histy
Version: 1.0.3
Summary: A command-line tool for generating histograms from timestamped logs
Home-page: https://github.com/fmhall/histy
Author: Mason Hall
Author-email: masonhall@gmail.com
License: UNKNOWN
Platform: UNKNOWN
Classifier: Programming Language :: Python :: 3
Classifier: License :: OSI Approved :: MIT License
Classifier: Operating System :: OS Independent
Requires-Python: >=3.6
